kumo_turbo-1.1.5.dist-info/licenses/LICENSE
turbo/__init__.py
turbo/_myclass.py
turbo/_status.py
turbo/_turbopy.cpython-39-x86_64-linux-gnu.so
turbo/app.py
turbo/command_name.py
turbo/flat_hash_map.pxd
turbo/status.pxd
turbo/flags/__init__.py
turbo/flags/_argument_parser.py
turbo/flags/_defines.py
turbo/flags/_exceptions.py
turbo/flags/_flag.py
turbo/flags/_flagvalues.py
turbo/flags/_helpers.py
turbo/flags/_validators.py
turbo/flags/_validators_classes.py
turbo/flags/argparse_flags.py
turbo/logging/__init__.py
turbo/logging/converter.py
kumo_turbo-1.1.5.dist-info/METADATA
kumo_turbo-1.1.5.dist-info/WHEEL
kumo_turbo-1.1.5.dist-info/top_level.txt
kumo_turbo-1.1.5.dist-info/RECORD
